<?xml version="1.0" encoding="utf-8"?>
	<annotation>
		<filename>08_11_2019-airpollution_234_19737819_192539446_jpg.rf.113e45f57dba09fde40d8490ae957fe6.txt</filename>
		<path>valid\labels\08_11_2019-airpollution_234_19737819_192539446_jpg.rf.113e45f57dba09fde40d8490ae957fe6.txt</path>
		<source>
			<database>Unknown</database>
		</source>
		<size>
			<width>416</width>
			<height>416</height>
			<depth>3</depth>
		</size>
		<folder>08_11_2019-airpollution_234_19737819_192539446_jpg.rf.113e45f57dba09fde40d8490ae957fe6.txt</folder>
		<object>
			<name>mask</name>
			<pose>Unspecified</pose>
			<truncated>0</truncated>
			<difficult>0</difficult>
			<bndbox>
				<xmin>149</xmin>
				<ymin>199</ymin>
				<xmax>302</xmax>
				<ymax>374</ymax>
			</bndbox>
		</object>
		<object>
			<name>mask</name>
			<pose>Unspecified</pose>
			<truncated>0</truncated>
			<difficult>0</difficult>
			<bndbox>
				<xmin>168</xmin>
				<ymin>37</ymin>
				<xmax>303</xmax>
				<ymax>168</ymax>
			</bndbox>
		</object>
	</annotation>
